README.rst
setup.cfg
setup.py
pyclickup/__init__.py
pyclickup/globals.py
pyclickup.egg-info/PKG-INFO
pyclickup.egg-info/SOURCES.txt
pyclickup.egg-info/dependency_links.txt
pyclickup.egg-info/not-zip-safe
pyclickup.egg-info/requires.txt
pyclickup.egg-info/top_level.txt
pyclickup/models/__init__.py
pyclickup/models/client.py
pyclickup/models/error.py
pyclickup/test/__init__.py
pyclickup/test/conftest.py
pyclickup/test/helpers.py
pyclickup/test/test_pyclickup.py
pyclickup/utils/__init__.py
pyclickup/utils/text.py