Metadata-Version: 1.1
Name: pyclickup
Version: 0.0.9
Summary: A python wrapper for the ClickUp API
Home-page: https://github.com/jpetrucciani/pyclickup.git
Author: Jacobi Petrucciani
Author-email: jacobi@mimirhq.com
License: LICENSE
Download-URL: https://github.com/jpetrucciani/pyclickup.git
Keywords: clickup python
Platform: UNKNOWN
Classifier: Programming Language :: Python :: 3
Classifier: Programming Language :: Python :: 3.5
Classifier: Programming Language :: Python :: 3.6
Classifier: Programming Language :: Python :: 3.7
